./.gitignore
./PKG-INFO
./README.md
./pyproject.toml
./hiagent_components/__init__.py
./hiagent_components/agent/__init__.py
./hiagent_components/agent/base.py
./hiagent_components/base/__init__.py
./hiagent_components/base/base.py
./hiagent_components/base/utils.py
./hiagent_components/integrations/__init__.py
./hiagent_components/integrations/langchain/__init__.py
./hiagent_components/integrations/langchain/retriever.py
./hiagent_components/integrations/langchain/tool.py
./hiagent_components/integrations/mcp/tool.py
./hiagent_components/retriever/__init__.py
./hiagent_components/retriever/base.py
./hiagent_components/tool/__init__.py
./hiagent_components/tool/base.py
./hiagent_components/tool/tool.py
./hiagent_components/utils/__init__.py
./hiagent_components/utils/schema.py
./hiagent_components/workflow/__init__.py
./hiagent_components/workflow/base.py
./hiagent_components/workflow/utils.py
hiagent_components-2.0.2.dist-info/METADATA
hiagent_components-2.0.2.dist-info/WHEEL
hiagent_components-2.0.2.dist-info/RECORD
