Metadata-Version: 2.4
Name: hiagent-components
Version: 2.0.2
Summary: Add your description here
Requires-Python: >=3.10
Requires-Dist: hiagent-api<3.0.0,>=0.1.0
Requires-Dist: json-schema-to-pydantic>=0.2.6
Requires-Dist: pydantic>=2.11.5
Requires-Dist: python-dotenv>=1.1.0
Requires-Dist: strenum>=0.4.15
Requires-Dist: tenacity>=9.1.2
